[
  {
    "id": 1,
    "version": 1.0,
    "app": "App de Salud",
    "enviroment": "Sandbox",
    "apis": "Salud colectiva",
    "traffic": "22k",
    "company": "Organización nombre",
    "creationDate": "12/01/2022 - 10:34",
    "lastModification": "12/01/2022 - 10:34",
    "status": "APROBADO",
    "description": "Descripción de la aplicación"
  },
  {
    "id": 2,
    "version": 1.0,
    "app": "App de Riesgos generales",
    "enviroment": "Sandbox / Producción",
    "apis": "Salud colectiva",
    "traffic": "22k",
    "company": "Organización nombre",
    "creationDate": "12/01/2022 - 10:34",
    "lastModification": "12/01/2022 - 10:34",
    "status": "SOLICITADO",
    "description": "Descripción de la aplicación"
  },
  {
    "id": 3,
    "version": 1.0,
    "app": "App Vehicular",
    "enviroment": "Sandbox",
    "apis": "Salud colectiva",
    "traffic": "22k",
    "company": "Organización nombre",
    "creationDate": "12/01/2022 - 10:34",
    "lastModification": "12/01/2022 - 10:34",
    "status": "APROBADO",
    "description": "Descripción de la aplicación"
  },  
  {
    "id": 4,
    "version": 1.0,
    "app": "App de Salud",
    "enviroment": "Sandbox",
    "apis": "Salud colectiva",
    "traffic": "22k",
    "company": "Organización nombre",
    "creationDate": "12/01/2022 - 10:34",
    "lastModification": "12/01/2022 - 10:34",
    "status": "SOLICITADO",
    "description": "Descripción de la aplicación"
  },
  {
    "id": 5,
    "version": 1.5,
    "app": "App de Riesgos generales",
    "enviroment": "Sandbox / Producción",
    "apis": "Salud colectiva",
    "traffic": "22k",
    "company": "Organización nombre",
    "creationDate": "12/01/2022 - 10:34",
    "lastModification": "12/01/2022 - 10:34",
    "status": "APROBADO",
    "description": "Descripción de la aplicación"
  },
  {
    "id": 6,
    "version": 1.5,
    "app": "App Vehicular",
    "enviroment": "Sandbox",
    "apis": "Salud colectiva",
    "traffic": "22k",
    "company": "Organización nombre",
    "creationDate": "12/01/2022 - 10:34",
    "lastModification": "12/01/2022 - 10:34",
    "status": "SOLICITADO",
    "description": "Descripción de la aplicación"
  },  
  {
    "id": 7,
    "version": 2.0,
    "app": "App de Salud",
    "enviroment": "Sandbox",
    "apis": "Salud colectiva",
    "traffic": "22k",
    "company": "Organización nombre",
    "creationDate": "12/01/2022 - 10:34",
    "lastModification": "12/01/2022 - 10:34",
    "status": "SOLICITADO",
    "description": "Descripción de la aplicación"
  },
  {
    "id": 8,
    "version": 2.0,
    "app": "App de Riesgos generales",
    "enviroment": "Sandbox / Producción",
    "apis": "Salud colectiva",
    "traffic": "22k",
    "company": "Organización nombre",
    "creationDate": "12/01/2022 - 10:34",
    "lastModification": "12/01/2022 - 10:34",
    "status": "APROBADO",
    "description": "Descripción de la aplicación"
  },
  {
    "id": 9,
    "version": 2.5,
    "app": "App Vehicular",
    "enviroment": "Sandbox",
    "apis": "Salud colectiva",
    "traffic": "22k",
    "company": "Organización nombre",
    "creationDate": "12/01/2022 - 10:34",
    "lastModification": "12/01/2022 - 10:34",
    "status": "APROBADO",
    "description": "Descripción de la aplicación"
  },
  {
    "id": 10,
    "version": 2.5,
    "app": "App de Salud",
    "enviroment": "Sandbox",
    "apis": "Salud colectiva",
    "traffic": "22k",
    "company": "Organización nombre",
    "creationDate": "12/01/2022 - 10:34",
    "lastModification": "12/01/2022 - 10:34",
    "status": "SOLICITADO",
    "description": "Descripción de la aplicación"
  },
  {
    "id": 11,
    "version": 3.0,
    "app": "App de Riesgos generales",
    "enviroment": "Sandbox / Producción",
    "apis": "Salud colectiva",
    "traffic": "22k",
    "company": "Organización nombre",
    "creationDate": "12/01/2022 - 10:34",
    "lastModification": "12/01/2022 - 10:34",
    "status": "APROBADO",
    "description": "Descripción de la aplicación"
  },
  {
    "id": 12,
    "version": 3.0,
    "app": "App Vehicular",
    "enviroment": "Sandbox",
    "apis": "Salud colectiva",
    "traffic": "22k",
    "company": "Organización nombre",
    "creationDate": "12/01/2022 - 10:34",
    "lastModification": "12/01/2022 - 10:34",
    "status": "SOLICITADO",
    "description": "Descripción de la aplicación"
  }
]
